Workbook

Sheet Cover
B4: CLOUD HR SAAS
B6: Integrated FP&A Financial Model
B8: B2B HR SaaS | 3-Tier Subscription | 6-Year Projection
B10: Prepared by: Megha Dalmia,MBA | Model Version: 1.0 | April 2026
B14: Model Navigation
B16: → Assumptions | C16: All model drivers pricing, growth, costs, margins
B17: → Revenue Model | C17: MRR/ARR build, cohort logic, churn, expansion
B18: → P&L | C18: Full Income Statement Revenue to Net Income
B19: → Unit Economics | C19: CAC, LTV, Payback, Contribution Margin
B20: → Headcount | C20: Hiring plan and people costs
B21: → Cash Flow | C21: Operating, Investing, Financing activities
B22: → Balance Sheet | C22: Assets, Liabilities, Equity
B23: → KPI Dashboard | C23: Executive summary of key metrics
B24: → Scenario Analysis | C24: Base / Bull / Bear case toggle
B27: Color Legend
B28: Sample | C28: Blue text = Hardcoded input / assumption (user editable)
B29: Sample | C29: Black text = Formula / calculated value
B30: Sample | C30: Green text = Cross-sheet link
B31: Sample | C31: Yellow background = Key assumption review before sharing

Sheet Assumptions
A1: CLOUDHR SAAS — MODEL ASSUMPTIONS
A2: Blue = hardcoded input | Yellow background = key assumption
A4: Assumption | B4: FY2024A | C4: FY2025E | D4: FY2026E | E4: FY2027E | F4: FY2028E | G4: FY2029E | H4: Notes
A5: PRICING — ANNUAL CONTRACT VALUE (ACV) PER CUSTOMER ($)
A6: Starter tier ACV ($) | B6: 3600 | C6: 3600 | D6: 3780 | E6: 3969 | F6: 4167 | G6: 4376 | H6: Base price; 5% annual increase yr3+
A7: Growth tier ACV ($) | B7: 9600 | C7: 9600 | D7: 10080 | E7: 10584 | F7: 11113 | G7: 11669 | H7: Mid-market segment
A8: Enterprise tier ACV ($) | B8: 24000 | C8: 24000 | D8: 25200 | E8: 26460 | F8: 27783 | G8: 29172 | H8: Annual negotiated contracts
A9: CUSTOMER COUNTS — END OF PERIOD
A10: Starter customers | B10: 320 | C10: 480 | D10: 680 | E10: 900 | F10: 1100 | G10: 1280 | H10: SMB segment
A11: Growth customers | B11: 110 | C11: 175 | D11: 255 | E11: 340 | F11: 420 | G11: 490 | H11: Mid-market
A12: Enterprise customers | B12: 28 | C12: 45 | D12: 68 | E12: 95 | F12: 125 | G12: 150 | H12: Direct sales motion
A13: CHURN & EXPANSION
A14: Gross churn rate (annual) | B14: 0.18 | C14: 0.16 | D14: 0.14 | E14: 0.12 | F14: 0.11 | G14: 0.1 | H14: Logo churn; improves with NPS
A15: Net Revenue Retention | B15: 1.05 | C15: 1.08 | D15: 1.1 | E15: 1.12 | F15: 1.14 | G15: 1.15 | H15: Expansion > churn target
A16: COST OF REVENUE
A17: Hosting & infra (% rev) | B17: 0.08 | C17: 0.07 | D17: 0.065 | E17: 0.06 | F17: 0.055 | G17: 0.05 | H17: AWS/GCP — scales with volume
A18: Customer success (% rev) | B18: 0.1 | C18: 0.09 | D18: 0.085 | E18: 0.08 | F18: 0.075 | G18: 0.07 | H18: CS team cost
A19: Support & ops (% rev) | B19: 0.06 | C19: 0.055 | D19: 0.05 | E19: 0.045 | F19: 0.04 | G19: 0.038 | H19: L1/L2 support
A20: OPERATING EXPENSES
A21: R&D (% rev) | B21: 0.32 | C21: 0.28 | D21: 0.25 | E21: 0.22 | F21: 0.2 | G21: 0.18 | H21: Product + engineering
A22: Sales & Marketing (% rev) | B22: 0.38 | C22: 0.34 | D22: 0.3 | E22: 0.27 | F22: 0.25 | G22: 0.23 | H22: CAC-heavy early years
A23: G&A (% rev) | B23: 0.14 | C23: 0.12 | D23: 0.1 | E23: 0.09 | F23: 0.08 | G23: 0.075 | H23: Finance, Legal, HR
A24: UNIT ECONOMICS
A25: Blended CAC ($) | B25: 4200 | C25: 3900 | D25: 3600 | E25: 3300 | F25: 3100 | G25: 2900 | H25: Fully-loaded S&M / new logo
A26: Avg contract length (yrs) | B26: 1 | C26: 1 | D26: 1.2 | E26: 1.5 | F26: 1.5 | G26: 2 | H26: Moving to multi-year deals
A27: BALANCE SHEET & CASH
A28: Days Sales Outstanding | B28: 35 | C28: 32 | D28: 30 | E28: 28 | F28: 28 | G28: 28 | H28: Accounts receivable days
A29: CapEx (% rev) | B29: 0.03 | C29: 0.025 | D29: 0.02 | E29: 0.02 | F29: 0.018 | G29: 0.015 | H29: Leasehold + equipment
A30: Tax rate | B30: 0 | C30: 0 | D30: 0 | E30: 0.21 | F30: 0.21 | G30: 0.21 | H30: NOL shield until FY2027
A31: Opening cash ($000s) | B31: 5000 | H31: Seed + Series A raised

Sheet Revenue Model
A1: CLOUDHR SAAS — REVENUE MODEL
A3: Metric | B3: FY2024A | C3: FY2025E | D3: FY2026E | E3: FY2027E | F3: FY2028E | G3: FY2029E | H3: Notes
A4: TIER 1 — STARTER
A5: Customers (EOP) | B5: 320 | C5: 480 | D5: 680 | E5: 900 | F5: 1100 | G5: 1280 | H5: From Assumptions
A6: ACV per customer ($) | B6: 3600 | C6: 3600 | D6: 3780 | E6: 3969 | F6: 4167 | G6: 4376 | H6: 5% price increase yr3+
A7: Starter Revenue ($000s) | B7: =B5*B6/1000 -> 1152 | C7: =C5*C6/1000 -> 1728 | D7: =D5*D6/1000 -> 2570.4 | E7: =E5*E6/1000 -> 3572.1 | F7: =F5*F6/1000 -> 4583.7 | G7: =G5*G6/1000 -> 5601.28 | H7: Customers × ACV / 1000
A8: TIER 2 — GROWTH
A9: Customers (EOP) | B9: 110 | C9: 175 | D9: 255 | E9: 340 | F9: 420 | G9: 490
A10: ACV per customer ($) | B10: 9600 | C10: 9600 | D10: 10080 | E10: 10584 | F10: 11113 | G10: 11669
A11: Growth Revenue ($000s) | B11: =B9*B10/1000 -> 1056 | C11: =C9*C10/1000 -> 1680 | D11: =D9*D10/1000 -> 2570.4 | E11: =E9*E10/1000 -> 3598.56 | F11: =F9*F10/1000 -> 4667.46 | G11: =G9*G10/1000 -> 5717.81
A12: TIER 3 — ENTERPRISE
A13: Customers (EOP) | B13: 28 | C13: 45 | D13: 68 | E13: 95 | F13: 125 | G13: 150
A14: ACV per customer ($) | B14: 24000 | C14: 24000 | D14: 25200 | E14: 26460 | F14: 27783 | G14: 29172
A15: Enterprise Revenue ($000s) | B15: =B13*B14/1000 -> 672 | C15: =C13*C14/1000 -> 1080 | D15: =D13*D14/1000 -> 1713.6 | E15: =E13*E14/1000 -> 2513.7 | F15: =F13*F14/1000 -> 3472.875 | G15: =G13*G14/1000 -> 4375.8
A16: TOTAL REVENUE SUMMARY
A17: TOTAL REVENUE ($000s) | B17: =B7+B11+B15 -> 2880 | C17: =C7+C11+C15 -> 4488 | D17: =D7+D11+D15 -> 6854.4 | E17: =E7+E11+E15 -> 9684.36 | F17: =F7+F11+F15 -> 12724.035 | G17: =G7+G11+G15 -> 15694.89 | H17: Sum of all tiers
A18: Total Customers | B18: =B5+B9+B13 -> 458 | C18: =C5+C9+C13 -> 700 | D18: =D5+D9+D13 -> 1003 | E18: =E5+E9+E13 -> 1335 | F18: =F5+F9+F13 -> 1645 | G18: =G5+G9+G13 -> 1920 | H18: Total logos
A19: ARR ($000s) | B19: =B17 -> 2880 | C19: =C17 -> 4488 | D19: =D17 -> 6854.4 | E19: =E17 -> 9684.36 | F19: =F17 -> 12724.035 | G19: =G17 -> 15694.89 | H19: Annual Recurring Revenue = Total Rev (all subscription)
A20: YoY Revenue Growth | B20: N/A | C20: =IF(B17=0,"N/A",(C17-B17)/B17) -> 0.55833333 | D20: =(D17-C17)/C17 -> 0.52727273 | E20: =(E17-D17)/D17 -> 0.41286765 | F20: =(F17-E17)/E17 -> 0.31387464 | G20: =(G17-F17)/F17 -> 0.23348372 | H20: Period over period
A21: MRR ($000s) | B21: =B17/12 -> 240 | C21: =C17/12 -> 374 | D21: =D17/12 -> 571.2 | E21: =E17/12 -> 807.03 | F21: =F17/12 -> 1060.3363 | G21: =G17/12 -> 1307.9075 | H21: Monthly Recurring Revenue
A22: ARPU — Blended ($) | B22: =IF(B18=0,0,B17*1000/B18) -> 6288.2096 | C22: =IF(C18=0,0,C17*1000/C18) -> 6411.4286 | D22: =IF(D18=0,0,D17*1000/D18) -> 6833.8983 | E22: =IF(E18=0,0,E17*1000/E18) -> 7254.2022 | F22: =IF(F18=0,0,F17*1000/F18) -> 7734.9757 | G22: =IF(G18=0,0,G17*1000/G18) -> 8174.4219 | H22: Average Revenue Per User

Sheet P&L
A1: CLOUDHR SAAS — INCOME STATEMENT (P&L)
A2: All figures in $000s unless stated
A4: Line Item | B4: FY2024A | C4: FY2025E | D4: FY2026E | E4: FY2027E | F4: FY2028E | G4: FY2029E | H4: Driver
A5: Revenue | B5: ='Revenue Model'!B17 -> 2880 | C5: ='Revenue Model'!C17 -> 4488 | D5: ='Revenue Model'!D17 -> 6854.4 | E5: ='Revenue Model'!E17 -> 9684.36 | F5: ='Revenue Model'!F17 -> 12724.035 | G5: ='Revenue Model'!G17 -> 15694.89 | H5: Linked from Revenue Model
A6: COST OF REVENUE
A7: Hosting & Infrastructure | B7: =-B5*0.08 -> -230.4 | C7: =-C5*0.07 -> -314.16 | D7: =-D5*0.065 -> -445.536 | E7: =-E5*0.06 -> -581.0616 | F7: =-F5*0.055 -> -699.82192 | G7: =-G5*0.05 -> -784.7445 | H7: % of revenue per Assumptions
A8: Customer Success | B8: =-B5*0.1 -> -288 | C8: =-C5*0.09 -> -403.92 | D8: =-D5*0.085 -> -582.624 | E8: =-E5*0.08 -> -774.7488 | F8: =-F5*0.075 -> -954.30262 | G8: =-G5*0.07 -> -1098.6423
A9: Support & Operations | B9: =-B5*0.06 -> -172.8 | C9: =-C5*0.055 -> -246.84 | D9: =-D5*0.05 -> -342.72 | E9: =-E5*0.045 -> -435.7962 | F9: =-F5*0.04 -> -508.9614 | G9: =-G5*0.038 -> -596.40582
A10: Total Cost of Revenue | B10: =B7+B8+B9 -> -691.2 | C10: =C7+C8+C9 -> -964.92 | D10: =D7+D8+D9 -> -1370.88 | E10: =E7+E8+E9 -> -1791.6066 | F10: =F7+F8+F9 -> -2163.086 | G10: =G7+G8+G9 -> -2479.7926
A11: GROSS PROFIT | B11: =B5+B10 -> 2188.8 | C11: =C5+C10 -> 3523.08 | D11: =D5+D10 -> 5483.52 | E11: =E5+E10 -> 7892.7534 | F11: =F5+F10 -> 10560.949 | G11: =G5+G10 -> 13215.097
A12: Gross Margin % | B12: =IF(B5=0,0,B11/B5) -> 0.76 | C12: =IF(C5=0,0,C11/C5) -> 0.785 | D12: =IF(D5=0,0,D11/D5) -> 0.8 | E12: =IF(E5=0,0,E11/E5) -> 0.815 | F12: =IF(F5=0,0,F11/F5) -> 0.83 | G12: =IF(G5=0,0,G11/G5) -> 0.842 | H12: Target: 70%+ by FY2027
A13: OPERATING EXPENSES
A14: R&D | B14: =-B5*0.32 -> -921.6 | C14: =-C5*0.28 -> -1256.64 | D14: =-D5*0.25 -> -1713.6 | E14: =-E5*0.22 -> -2130.5592 | F14: =-F5*0.2 -> -2544.807 | G14: =-G5*0.18 -> -2825.0802 | H14: Declining as % of rev
A15: Sales & Marketing | B15: =-B5*0.38 -> -1094.4 | C15: =-C5*0.34 -> -1525.92 | D15: =-D5*0.3 -> -2056.32 | E15: =-E5*0.27 -> -2614.7772 | F15: =-F5*0.25 -> -3181.0087 | G15: =-G5*0.23 -> -3609.8247
A16: G&A | B16: =-B5*0.14 -> -403.2 | C16: =-C5*0.12 -> -538.56 | D16: =-D5*0.1 -> -685.44 | E16: =-E5*0.09 -> -871.5924 | F16: =-F5*0.08 -> -1017.9228 | G16: =-G5*0.075 -> -1177.1167
A17: Total OpEx | B17: =B14+B15+B16 -> -2419.2 | C17: =C14+C15+C16 -> -3321.12 | D17: =D14+D15+D16 -> -4455.36 | E17: =E14+E15+E16 -> -5616.9288 | F17: =F14+F15+F16 -> -6743.7386 | G17: =G14+G15+G16 -> -7612.0216
A18: EBITDA | B18: =B11+B17 -> -230.4 | C18: =C11+C17 -> 201.96 | D18: =D11+D17 -> 1028.16 | E18: =E11+E17 -> 2275.8246 | F18: =F11+F17 -> 3817.2105 | G18: =G11+G17 -> 5603.0757 | H18: Earnings Before Interest, Tax, D&A
A19: EBITDA Margin % | B19: =IF(B5=0,0,B18/B5) -> -0.08 | C19: =IF(C5=0,0,C18/C5) -> 0.045 | D19: =IF(D5=0,0,D18/D5) -> 0.15 | E19: =IF(E5=0,0,E18/E5) -> 0.235 | F19: =IF(F5=0,0,F18/F5) -> 0.3 | G19: =IF(G5=0,0,G18/G5) -> 0.357
A20: D&A | B20: =-B5*0.02 -> -57.6 | C20: =-C5*0.02 -> -89.76 | D20: =-D5*0.018 -> -123.3792 | E20: =-E5*0.016 -> -154.94976 | F20: =-F5*0.015 -> -190.86052 | G20: =-G5*0.015 -> -235.42335 | H20: Depreciation & Amortization
A21: EBIT (Operating Income) | B21: =B18+B20 -> -288 | C21: =C18+C20 -> 112.2 | D21: =D18+D20 -> 904.7808 | E21: =E18+E20 -> 2120.8748 | F21: =F18+F20 -> 3626.35 | G21: =G18+G20 -> 5367.6524
A22: Interest Income / (Expense) | B22: 50 | C22: 80 | D22: 100 | E22: 120 | F22: 150 | G22: 200 | H22: Interest on cash balance
A23: EBT (Pre-Tax Income) | B23: =B21+B22 -> -238 | C23: =C21+C22 -> 192.2 | D23: =D21+D22 -> 1004.7808 | E23: =E21+E22 -> 2240.8748 | F23: =F21+F22 -> 3776.35 | G23: =G21+G22 -> 5567.6524
A24: Income Tax | B24: =IF(B23>0,-B23*0,0) -> 0 | C24: =IF(C23>0,-C23*0,0) -> 0 | D24: =IF(D23>0,-D23*0,0) -> 0 | E24: =IF(E23>0,-E23*0.21,0) -> -470.58372 | F24: =IF(F23>0,-F23*0.21,0) -> -793.03349 | G24: =IF(G23>0,-G23*0.21,0) -> -1169.207 | H24: NOL shield FY2024-26; 21% thereafter
A25: NET INCOME | B25: =B23+B24 -> -238 | C25: =C23+C24 -> 192.2 | D25: =D23+D24 -> 1004.7808 | E25: =E23+E24 -> 1770.2911 | F25: =F23+F24 -> 2983.3165 | G25: =G23+G24 -> 4398.4454
A26: Net Income Margin % | B26: =IF(B5=0,0,B25/B5) -> -0.082638889 | C26: =IF(C5=0,0,C25/C5) -> 0.042825312 | D26: =IF(D5=0,0,D25/D5) -> 0.14658917 | E26: =IF(E5=0,0,E25/E5) -> 0.18279898 | F26: =IF(F5=0,0,F25/F5) -> 0.23446308 | G26: =IF(G5=0,0,G25/G5) -> 0.28024697

Sheet Unit Economics
A1: CLOUDHR SAAS — UNIT ECONOMICS
A3: Metric | B3: FY2024A | C3: FY2025E | D3: FY2026E | E3: FY2027E | F3: FY2028E | G3: FY2029E | H3: Formula / Notes
A4: CUSTOMER ACQUISITION COST (CAC)
A5: Blended CAC ($) | B5: 4200 | C5: 3900 | D5: 3600 | E5: 3300 | F5: 3100 | G5: 2900 | H5: Fully-loaded S&M ÷ new logos
A6: New Logos Added | B6: ='Revenue Model'!B18 -> 458 | C6: ='Revenue Model'!C18-'Revenue Model'!B18 -> 242 | D6: ='Revenue Model'!D18-'Revenue Model'!C18 -> 303 | E6: ='Revenue Model'!E18-'Revenue Model'!D18 -> 332 | F6: ='Revenue Model'!F18-'Revenue Model'!E18 -> 310 | G6: ='Revenue Model'!G18-'Revenue Model'!F18 -> 275 | H6: EOP customers delta
A7: Total CAC Spend ($000s) | B7: =B5*B6/1000 -> 1923.6 | C7: =C5*C6/1000 -> 943.8 | D7: =D5*D6/1000 -> 1090.8 | E7: =E5*E6/1000 -> 1095.6 | F7: =F5*F6/1000 -> 961 | G7: =G5*G6/1000 -> 797.5 | H7: CAC × new logos
A8: LIFETIME VALUE (LTV)
A9: ARPU — Blended ($ annual) | B9: =IF('Revenue Model'!B18=0,0,'Revenue Model'!B17*1000/'Revenue Model'!B18) -> 6288.2096 | C9: =IF('Revenue Model'!C18=0,0,'Revenue Model'!C17*1000/'Revenue Model'!C18) -> 6411.4286 | D9: =IF('Revenue Model'!D18=0,0,'Revenue Model'!D17*1000/'Revenue Model'!D18) -> 6833.8983 | E9: =IF('Revenue Model'!E18=0,0,'Revenue Model'!E17*1000/'Revenue Model'!E18) -> 7254.2022 | F9: =IF('Revenue Model'!F18=0,0,'Revenue Model'!F17*1000/'Revenue Model'!F18) -> 7734.9757 | G9: =IF('Revenue Model'!G18=0,0,'Revenue Model'!G17*1000/'Revenue Model'!G18) -> 8174.4219 | H9: Rev × 1000 / total customers
A10: Gross Margin % | B10: ='P&L'!B12 -> 0.76 | C10: ='P&L'!C12 -> 0.785 | D10: ='P&L'!D12 -> 0.8 | E10: ='P&L'!E12 -> 0.815 | F10: ='P&L'!F12 -> 0.83 | G10: ='P&L'!G12 -> 0.842 | H10: Linked from P&L
A11: Annual Gross Churn Rate | B11: 0.18 | C11: 0.16 | D11: 0.14 | E11: 0.12 | F11: 0.11 | G11: 0.1 | H11: From Assumptions
A12: Avg Customer Lifetime (yrs) | B12: =IF(B11=0,0,1/B11) -> 5.5555556 | C12: =IF(C11=0,0,1/C11) -> 6.25 | D12: =IF(D11=0,0,1/D11) -> 7.1428571 | E12: =IF(E11=0,0,1/E11) -> 8.3333333 | F12: =IF(F11=0,0,1/F11) -> 9.0909091 | G12: =IF(G11=0,0,1/G11) -> 10 | H12: 1 / Churn Rate
A13: LTV ($) | B13: =B9*B10*B12 -> 26550.218 | C13: =C9*C10*C12 -> 31456.071 | D13: =D9*D10*D12 -> 39050.847 | E13: =E9*E10*E12 -> 49268.124 | F13: =F9*F10*F12 -> 58363.907 | G13: =G9*G10*G12 -> 68828.632 | H13: ARPU × GM% × Avg Life
A14: LTV:CAC & PAYBACK
A15: LTV:CAC Ratio | B15: =IF(B5=0,0,B13/B5) -> 6.3214806 | C15: =IF(C5=0,0,C13/C5) -> 8.0656593 | D15: =IF(D5=0,0,D13/D5) -> 10.847458 | E15: =IF(E5=0,0,E13/E5) -> 14.929734 | F15: =IF(F5=0,0,F13/F5) -> 18.827067 | G15: =IF(G5=0,0,G13/G5) -> 23.734011 | H15: Target: >3x for healthy SaaS
A16: CAC Payback Period (months) | B16: =IF(B9*B10=0,0,B5/(B9*B10)*12) -> 10.546053 | C16: =IF(C9*C10=0,0,C5/(C9*C10)*12) -> 9.2986818 | D16: =IF(D9*D10=0,0,D5/(D9*D10)*12) -> 7.9017857 | E16: =IF(E9*E10=0,0,E5/(E9*E10)*12) -> 6.6980428 | F16: =IF(F9*F10=0,0,F5/(F9*F10)*12) -> 5.7943656 | G16: =IF(G9*G10=0,0,G5/(G9*G10)*12) -> 5.0560354 | H16: Target: <18 months
A17: Magic Number (Efficiency) | B17: =IF(B7=0,0,(C5-B5)*B10/B7) -> -0.11852776 | C17: =IF(B7=0,0,(C5-B5)*B10/B7) -> -0.11852776 | D17: =IF(C7=0,0,(D5-C5)*C10/C7) -> -0.2495232 | E17: =IF(D7=0,0,(E5-D5)*D10/D7) -> -0.220022 | F17: =IF(E7=0,0,(F5-E5)*E10/E7) -> -0.14877693 | G17: =IF(F7=0,0,(G5-F5)*F10/F7) -> -0.17273673 | H17: ΔRev×GM / S&M spend; >0.75 = efficient

Sheet Headcount
A1: CLOUDHR SAAS — HEADCOUNT & PEOPLE COSTS
A3: Department / Role | B3: FY2024A | C3: FY2025E | D3: FY2026E | E3: FY2027E | F3: FY2028E | G3: FY2029E | H3: Notes
A4: ENGINEERING & PRODUCT
A5: Engineering | B5: 8 | C5: 12 | D5: 18 | E5: 24 | F5: 30 | G5: 35
A6: Product Mgmt | B6: 3 | C6: 4 | D6: 6 | E6: 8 | F6: 10 | G6: 12
A7: Design | B7: 2 | C7: 3 | D7: 4 | E7: 5 | F7: 6 | G7: 7
A8: ENGINEERING & PRODUCT Total | B8: =SUM(B5:B7) -> 13 | C8: =SUM(C5:C7) -> 19 | D8: =SUM(D5:D7) -> 28 | E8: =SUM(E5:E7) -> 37 | F8: =SUM(F5:F7) -> 46 | G8: =SUM(G5:G7) -> 54
A9: SALES & MARKETING
A10: AEs / SDRs | B10: 6 | C10: 10 | D10: 15 | E10: 20 | F10: 26 | G10: 30
A11: Marketing | B11: 3 | C11: 5 | D11: 7 | E11: 9 | F11: 11 | G11: 13
A12: Customer Success | B12: 4 | C12: 7 | D12: 11 | E12: 15 | F12: 19 | G12: 22
A13: SALES & MARKETING Total | B13: =SUM(B10:B12) -> 13 | C13: =SUM(C10:C12) -> 22 | D13: =SUM(D10:D12) -> 33 | E13: =SUM(E10:E12) -> 44 | F13: =SUM(F10:F12) -> 56 | G13: =SUM(G10:G12) -> 65
A14: G&A
A15: Finance & Analytics | B15: 2 | C15: 3 | D15: 4 | E15: 5 | F15: 6 | G15: 7
A16: HR & Legal | B16: 1 | C16: 2 | D16: 3 | E16: 4 | F16: 5 | G16: 5
A17: Operations | B17: 2 | C17: 3 | D17: 4 | E17: 5 | F17: 6 | G17: 7
A18: G&A Total | B18: =SUM(B15:B17) -> 5 | C18: =SUM(C15:C17) -> 8 | D18: =SUM(D15:D17) -> 11 | E18: =SUM(E15:E17) -> 14 | F18: =SUM(F15:F17) -> 17 | G18: =SUM(G15:G17) -> 19
A19: TOTAL HEADCOUNT | B19: =B8+B13+B18 -> 31 | C19: =C8+C13+C18 -> 49 | D19: =D8+D13+D18 -> 72 | E19: =E8+E13+E18 -> 95 | F19: =F8+F13+F18 -> 119 | G19: =G8+G13+G18 -> 138
A21: PEOPLE COST BUILD
A22: Avg fully-loaded cost/head ($000s) | B22: 85 | C22: 88 | D22: 92 | E22: 96 | F22: 100 | G22: 104 | H22: Salary + benefits + equity; ~5% annual increase
A23: Total People Cost ($000s) | B23: =B19*B22 -> 2635 | C23: =C19*C22 -> 4312 | D23: =D19*D22 -> 6624 | E23: =E19*E22 -> 9120 | F23: =F19*F22 -> 11900 | G23: =G19*G22 -> 14352

Sheet Cash Flow
A1: CLOUDHR SAAS — CASH FLOW STATEMENT
A2: All figures in $000s
A4: Line Item | B4: FY2024A | C4: FY2025E | D4: FY2026E | E4: FY2027E | F4: FY2028E | G4: FY2029E
A5: OPERATING ACTIVITIES
A6: Net Income | B6: ='P&L'!B25 -> -238 | C6: ='P&L'!C25 -> 192.2 | D6: ='P&L'!D25 -> 1004.7808 | E6: ='P&L'!E25 -> 1770.2911 | F6: ='P&L'!F25 -> 2983.3165 | G6: ='P&L'!G25 -> 4398.4454 | H6: From P&L
A7: Add back: D&A | B7: =-'P&L'!B20 -> 57.6 | C7: =-'P&L'!C20 -> 89.76 | D7: =-'P&L'!D20 -> 123.3792 | E7: =-'P&L'!E20 -> 154.94976 | F7: =-'P&L'!F20 -> 190.86052 | G7: =-'P&L'!G20 -> 235.42335 | H7: Non-cash charge added back
A8: Change in Working Capital | B8: =-'P&L'!B5*0.035/12 -> -8.4 | C8: =-('P&L'!C5-'P&L'!B5)*0.032/12 -> -4.288 | D8: =-('P&L'!D5-'P&L'!C5)*0.03/12 -> -5.916 | E8: =-('P&L'!E5-'P&L'!D5)*0.028/12 -> -6.60324 | F8: =-('P&L'!F5-'P&L'!E5)*0.028/12 -> -7.092575 | G8: =-('P&L'!G5-'P&L'!F5)*0.028/12 -> -6.931995 | H8: DSO-driven AR movement
A9: Cash from Operations (CFO) | B9: =B6+B7+B8 -> -188.8 | C9: =C6+C7+C8 -> 277.672 | D9: =D6+D7+D8 -> 1122.244 | E9: =E6+E7+E8 -> 1918.6376 | F9: =F6+F7+F8 -> 3167.0844 | G9: =G6+G7+G8 -> 4626.9367
A10: INVESTING ACTIVITIES
A11: Capital Expenditures (CapEx) | B11: =-'P&L'!B5*0.03 -> -86.4 | C11: =-'P&L'!C5*0.025 -> -112.2 | D11: =-'P&L'!D5*0.02 -> -137.088 | E11: =-'P&L'!E5*0.02 -> -193.6872 | F11: =-'P&L'!F5*0.018 -> -229.03263 | G11: =-'P&L'!G5*0.015 -> -235.42335 | H11: % of revenue per Assumptions
A12: Cash from Investing (CFI) | B12: =B11 -> -86.4 | C12: =C11 -> -112.2 | D12: =D11 -> -137.088 | E12: =E11 -> -193.6872 | F12: =F11 -> -229.03263 | G12: =G11 -> -235.42335
A13: FINANCING ACTIVITIES
A14: Equity Raised | B14: 5000 | C14: 8000 | D14: 0 | E14: 0 | F14: 0 | G14: 0 | H14: Seed + Series A
A15: Debt Repayment | B15: 0 | C15: 0 | D15: 0 | E15: 0 | F15: 0 | G15: 0
A16: Cash from Financing (CFF) | B16: =B14+B15 -> 5000 | C16: =C14+C15 -> 8000 | D16: =D14+D15 -> 0 | E16: =E14+E15 -> 0 | F16: =F14+F15 -> 0 | G16: =G14+G15 -> 0
A17: NET CHANGE IN CASH | B17: =B9+B12+B16 -> 4724.8 | C17: =C9+C12+C16 -> 8165.472 | D17: =D9+D12+D16 -> 985.156 | E17: =E9+E12+E16 -> 1724.9504 | F17: =F9+F12+F16 -> 2938.0518 | G17: =G9+G12+G16 -> 4391.5134
A18: Opening Cash Balance | B18: 5000 | C18: =B17+B17 -> 9449.6 | D18: =C17+C17 -> 16330.944 | E18: =D17+D17 -> 1970.312 | F18: =E17+E17 -> 3449.9009 | G18: =F17+F17 -> 5876.1036 | H18: FY2024 opening = seed capital
A19: Closing Cash Balance | B19: =B18+B17 -> 9724.8 | C19: =C18+C17 -> 17615.072 | D19: =D18+D17 -> 17316.1 | E19: =E18+E17 -> 3695.2624 | F19: =F18+F17 -> 6387.9527 | G19: =G18+G17 -> 10267.617

Sheet KPI Dashboard
A1: CLOUDHR SAAS — KPI EXECUTIVE DASHBOARD
A2: Single source of truth for CFO / Board reporting
A4: KPI | B4: FY2024A | C4: FY2025E | D4: FY2026E | E4: FY2027E | F4: FY2028E | G4: FY2029E
A5: ── GROWTH ──
A6: Total Revenue ($000s) | B6: ='Revenue Model'!B17 -> 2880 | C6: ='Revenue Model'!C17 -> 4488 | D6: ='Revenue Model'!D17 -> 6854.4 | E6: ='Revenue Model'!E17 -> 9684.36 | F6: ='Revenue Model'!F17 -> 12724.035 | G6: ='Revenue Model'!G17 -> 15694.89
A7: YoY Revenue Growth | B7: N/A | C7: =('Revenue Model'!C17-'Revenue Model'!B17)/'Revenue Model'!B17 -> 0.55833333 | D7: =('Revenue Model'!D17-'Revenue Model'!C17)/'Revenue Model'!C17 -> 0.52727273 | E7: =('Revenue Model'!E17-'Revenue Model'!D17)/'Revenue Model'!D17 -> 0.41286765 | F7: =('Revenue Model'!F17-'Revenue Model'!E17)/'Revenue Model'!E17 -> 0.31387464 | G7: =('Revenue Model'!G17-'Revenue Model'!F17)/'Revenue Model'!F17 -> 0.23348372
A8: ARR ($000s) | B8: ='Revenue Model'!B17 -> 2880 | C8: ='Revenue Model'!C17 -> 4488 | D8: ='Revenue Model'!D17 -> 6854.4 | E8: ='Revenue Model'!E17 -> 9684.36 | F8: ='Revenue Model'!F17 -> 12724.035 | G8: ='Revenue Model'!G17 -> 15694.89
A9: Total Customers | B9: ='Revenue Model'!B18 -> 458 | C9: ='Revenue Model'!C18 -> 700 | D9: ='Revenue Model'!D18 -> 1003 | E9: ='Revenue Model'!E18 -> 1335 | F9: ='Revenue Model'!F18 -> 1645 | G9: ='Revenue Model'!G18 -> 1920
A10: ── PROFITABILITY ──
A11: Gross Profit ($000s) | B11: ='P&L'!B11 -> 2188.8 | C11: ='P&L'!C11 -> 3523.08 | D11: ='P&L'!D11 -> 5483.52 | E11: ='P&L'!E11 -> 7892.7534 | F11: ='P&L'!F11 -> 10560.949 | G11: ='P&L'!G11 -> 13215.097
A12: Gross Margin % | B12: ='P&L'!B12 -> 0.76 | C12: ='P&L'!C12 -> 0.785 | D12: ='P&L'!D12 -> 0.8 | E12: ='P&L'!E12 -> 0.815 | F12: ='P&L'!F12 -> 0.83 | G12: ='P&L'!G12 -> 0.842
A13: EBITDA ($000s) | B13: ='P&L'!B18 -> -230.4 | C13: ='P&L'!C18 -> 201.96 | D13: ='P&L'!D18 -> 1028.16 | E13: ='P&L'!E18 -> 2275.8246 | F13: ='P&L'!F18 -> 3817.2105 | G13: ='P&L'!G18 -> 5603.0757
A14: EBITDA Margin % | B14: ='P&L'!B19 -> -0.08 | C14: ='P&L'!C19 -> 0.045 | D14: ='P&L'!D19 -> 0.15 | E14: ='P&L'!E19 -> 0.235 | F14: ='P&L'!F19 -> 0.3 | G14: ='P&L'!G19 -> 0.357
A15: Net Income ($000s) | B15: ='P&L'!B25 -> -238 | C15: ='P&L'!C25 -> 192.2 | D15: ='P&L'!D25 -> 1004.7808 | E15: ='P&L'!E25 -> 1770.2911 | F15: ='P&L'!F25 -> 2983.3165 | G15: ='P&L'!G25 -> 4398.4454
A16: ── UNIT ECONOMICS ──
A17: CAC ($) | B17: ='Unit Economics'!B5 -> 4200 | C17: ='Unit Economics'!C5 -> 3900 | D17: ='Unit Economics'!D5 -> 3600 | E17: ='Unit Economics'!E5 -> 3300 | F17: ='Unit Economics'!F5 -> 3100 | G17: ='Unit Economics'!G5 -> 2900
A18: LTV ($) | B18: ='Unit Economics'!B13 -> 26550.218 | C18: ='Unit Economics'!C13 -> 31456.071 | D18: ='Unit Economics'!D13 -> 39050.847 | E18: ='Unit Economics'!E13 -> 49268.124 | F18: ='Unit Economics'!F13 -> 58363.907 | G18: ='Unit Economics'!G13 -> 68828.632
A19: LTV:CAC | B19: ='Unit Economics'!B15 -> 6.3214806 | C19: ='Unit Economics'!C15 -> 8.0656593 | D19: ='Unit Economics'!D15 -> 10.847458 | E19: ='Unit Economics'!E15 -> 14.929734 | F19: ='Unit Economics'!F15 -> 18.827067 | G19: ='Unit Economics'!G15 -> 23.734011
A20: CAC Payback (months) | B20: ='Unit Economics'!B16 -> 10.546053 | C20: ='Unit Economics'!C16 -> 9.2986818 | D20: ='Unit Economics'!D16 -> 7.9017857 | E20: ='Unit Economics'!E16 -> 6.6980428 | F20: ='Unit Economics'!F16 -> 5.7943656 | G20: ='Unit Economics'!G16 -> 5.0560354
A21: ── CASH ──
A22: CFO ($000s) | B22: ='Cash Flow'!B9 -> -188.8 | C22: ='Cash Flow'!C9 -> 277.672 | D22: ='Cash Flow'!D9 -> 1122.244 | E22: ='Cash Flow'!E9 -> 1918.6376 | F22: ='Cash Flow'!F9 -> 3167.0844 | G22: ='Cash Flow'!G9 -> 4626.9367
A23: Closing Cash ($000s) | B23: ='Cash Flow'!B19 -> 9724.8 | C23: ='Cash Flow'!C19 -> 17615.072 | D23: ='Cash Flow'!D19 -> 17316.1 | E23: ='Cash Flow'!E19 -> 3695.2624 | F23: ='Cash Flow'!F19 -> 6387.9527 | G23: ='Cash Flow'!G19 -> 10267.617

Sheet Scenario Analysis
A1: CLOUDHR SAAS — SCENARIO ANALYSIS
A2: Compares Base / Bull / Bear across key metrics for FY2029E
A4: Metric | B4: Base Case | C4: Bull Case (+20%) | D4: Bear Case (-20%) | E4: Bull vs Base | F4: Bear vs Base
A5: Revenue ($000s) | B5: ='Revenue Model'!G17 -> 15694.89 | C5: =B5*1.2 -> 18833.868 | D5: =B5*0.8 -> 12555.912 | E5: =C5-B5 -> 3138.978 | F5: =D5-B5 -> -3138.978
A6: Gross Margin % | B6: ='P&L'!G12 -> 0.842 | C6: =MIN(B6*1.05,1) -> 0.8841 | D6: =B6*0.95 -> 0.7999 | E6: =C6-B6 -> 0.0421 | F6: =D6-B6 -> -0.0421
A7: EBITDA ($000s) | B7: ='P&L'!G18 -> 5603.0757 | C7: =B7*1.2 -> 6723.6909 | D7: =B7*0.8 -> 4482.4606 | E7: =C7-B7 -> 1120.6151 | F7: =D7-B7 -> -1120.6151
A8: EBITDA Margin % | B8: ='P&L'!G19 -> 0.357 | C8: =MIN(B8*1.05,1) -> 0.37485 | D8: =B8*0.95 -> 0.33915 | E8: =C8-B8 -> 0.01785 | F8: =D8-B8 -> -0.01785
A9: Net Income ($000s) | B9: ='P&L'!G25 -> 4398.4454 | C9: =B9*1.2 -> 5278.1345 | D9: =B9*0.8 -> 3518.7563 | E9: =C9-B9 -> 879.68908 | F9: =D9-B9 -> -879.68908
A10: Total Customers | B10: ='Revenue Model'!G18 -> 1920 | C10: =B10*1.2 -> 2304 | D10: =B10*0.8 -> 1536 | E10: =C10-B10 -> 384 | F10: =D10-B10 -> -384
A11: LTV:CAC | B11: ='Unit Economics'!G15 -> 23.734011 | C11: =B11*1.2 -> 28.480813 | D11: =B11*0.8 -> 18.987209 | E11: =C11-B11 -> 4.7468022 | F11: =D11-B11 -> -4.7468022
A12: Closing Cash ($000s) | B12: ='Cash Flow'!G19 -> 10267.617 | C12: =B12*1.2 -> 12321.14 | D12: =B12*0.8 -> 8214.0936 | E12: =C12-B12 -> 2053.5234 | F12: =D12-B12 -> -2053.5234
